{
  "title": "男同性恋程序员的0和1属性对计算机程序运行优化的可行性分析",
  "subtitle": "",
  "body_text": "← Back to Septic Tank / 返回化粪池\n男同性恋程序员的0和1属性对计算机程序运行优化的可行性分析\nAuthor / 作者\n吉榭剑攀\nInstitution / 单位\n村立加利盾大学\nViscosity / 粘度\nStringy / 拉丝型\nDiscipline / 学科\n交叉 / Interdisciplinary\nSubmitted / 提交时间\n2026/3/3 00:18:42\nCo-Authors / 共同作者\n低村晚禾 · 村立加利盾大学\n共一\n甲何旺杠 · 乡立乡毋宁超算中心\nRate / 评价\n登录后可评分 / Sign in to rate\nSign In / 登录\n4.14\n/ 5\n36 ratings / 36个评分\nManuscript / 全文\nS.H.I.T JOURNAL PREPRINT\n本内容纯属整活，不代表任何学术观点或现实指导建议。请保持理智，切勿模仿。\nS.H.I.T JOURNAL PREPRINT\n本内容纯属整活，不代表任何学术观点或现实指导建议。请保持理智，切勿模仿。\nS.H.I.T JOURNAL PREPRINT\n本内容纯属整活，不代表任何学术观点或现实指导建议。请保持理智，切勿模仿。\nS.H.I.T JOURNAL PREPRINT\n本内容纯属整活，不代表任何学术观点或现实指导建议。请保持理智，切勿模仿。\nS.H.I.T JOURNAL PREPRINT\n本内容纯属整活，不代表任何学术观点或现实指导建议。请保持理智，切勿模仿。\nS.H.I.T JOURNAL PREPRINT\n本内容纯属整活，不代表任何学术观点或现实指导建议。请保持理智，切勿模仿。\nS.H.I.T JOURNAL PREPRINT\n本内容纯属整活，不代表任何学术观点或现实指导建议。请保持理智，切勿模仿。\nS.H.I.T JOURNAL PREPRINT\n本内容纯属整活，不代表任何学术观点或现实指导建议。请保持理智，切勿模仿。\nS.H.I.T JOURNAL PREPRINT\n本内容纯属整活，不代表任何学术观点或现实指导建议。请保持理智，切勿模仿。\nS.H.I.T JOURNAL PREPRINT\n本内容纯属整活，不代表任何学术观点或现实指导建议。请保持理智，切勿模仿。\nS.H.I.T JOURNAL PREPRINT\n本内容纯属整活，不代表任何学术观点或现实指导建议。请保持理智，切勿模仿。\nS.H.I.T JOURNAL PREPRINT\n本内容纯属整活，不代表任何学术观点或现实指导建议。请保持理智，切勿模仿。\nS.H.I.T JOURNAL PREPRINT\n本内容纯属整活，不代表任何学术观点或现实指导建议。请保持理智，切勿模仿。\nS.H.I.T JOURNAL PREPRINT\n本内容纯属整活，不代表任何学术观点或现实指导建议。请保持理智，切勿模仿。\nS.H.I.T JOURNAL PREPRINT\n本内容纯属整活，不代表任何学术观点或现实指导建议。请保持理智，切勿模仿。\n本内容纯属整活，不代表任何学术观点或现实指导建议。请保持理智，切勿模仿。\n← 上一页\n1 / 3\n下一页 →\n评论功能维护中，暂时关闭 / Comments are temporarily disabled\n8 条评论\n默认\n最新\n学术大屎\n图0还是冯诺1曼？这是个问题。\n2天前\n💩\n5\nNeko\n💩💩💩💩\n图灵老祖来了说是\n2天前\n💩\n2\n崩铁.张作霖\n💩💩💩💩💩\n1\n2天前\n💩\n1\nR\n💩💩💩💩\n真正的狗市\n2天前\n💩\n1\n飞行大雪绒\n0\n2天前\n💩\n1\n查看更多评论 (3)",
  "meta": {
    "author": "吉榭剑攀",
    "institution": "村立加利盾大学",
    "discipline": "交叉 / Interdisciplinary",
    "submitted": "2026/3/3 00:18:42",
    "viscosity": "Stringy / 拉丝型"
  },
  "url": "https://shitjournal.org/preprints/308ee7ee-ba1c-40d4-a07a-41a473e4d787",
  "slug": "308ee7ee-ba1c-40d4-a07a-41a473e4d787"
}