{
  "article": {
    "id": "e4965251-fa1d-4698-bb3d-094786f96613",
    "title": "抖音平台异性微信添加成功率的靶向提升体系构建与实证研究——基于个人多维度核心优势的全链路赋能",
    "file_name": "e4965251-fa1d-4698-bb3d-094786f96613",
    "pdf_url": "https://files.shitjournal.org/e4965251-fa1d-4698-bb3d-094786f96613.pdf",
    "tag": "meme",
    "zones": "septic",
    "status": "passed",
    "discipline": "interdisciplinary",
    "topic": "nan",
    "co_authors": [],
    "suggestions": "",
    "rating_count": 45,
    "avg_score": 4.333333333333333,
    "my_score": null,
    "created_at": "2026-03-03T19:11:13.344928Z",
    "author": {
      "id": "f6950d73-2611-4cac-b6eb-8ee6c5248f88",
      "display_name": "夜郎少女的梦",
      "avatar_url": null
    }
  },
  "comments": [],
  "fetched_at": "2026-03-10T16:04:11Z"
}