{
  "title": "基于触感反馈的粗糙度生物场探针原位检测及调控 In Situ Detection and Regulation of Roughness Biofield Probes Based on Haptic Feedback",
  "subtitle": "",
  "body_text": "← Back to The Latrine / 返回旱厕\n基于触感反馈的粗糙度生物场探针原位检测及调控 In Situ Detection and Regulation of Roughness Biofield Probes Based on Haptic Feedback\nAuthor / 作者\nShitwill Find Itsway\nInstitution / 单位\nSichuan Habber Institute of Technology\nViscosity / 粘度\nStringy / 拉丝型\nDiscipline / 学科\n交叉 / Interdisciplinary\nSubmitted / 提交时间\n2026/2/27 05:22:25\nSocial Media / 社交媒体\nGoldlike-Swift Baby on Erxian Bridge\nRate / 盲评\n登录后可评分 / Sign in to rate\nSign In / 登录\n评价进度 / Progress: 3 / 30\nManuscript / 全文\nS.H.I.T JOURNAL PREPRINT\n本内容纯属整活，不代表任何学术观点或现实指导建议。请保持理智，切勿模仿。\nS.H.I.T JOURNAL PREPRINT\n本内容纯属整活，不代表任何学术观点或现实指导建议。请保持理智，切勿模仿。\nS.H.I.T JOURNAL PREPRINT\n本内容纯属整活，不代表任何学术观点或现实指导建议。请保持理智，切勿模仿。\nS.H.I.T JOURNAL PREPRINT\n本内容纯属整活，不代表任何学术观点或现实指导建议。请保持理智，切勿模仿。\nS.H.I.T JOURNAL PREPRINT\n本内容纯属整活，不代表任何学术观点或现实指导建议。请保持理智，切勿模仿。\nS.H.I.T JOURNAL PREPRINT\n本内容纯属整活，不代表任何学术观点或现实指导建议。请保持理智，切勿模仿。\nS.H.I.T JOURNAL PREPRINT\n本内容纯属整活，不代表任何学术观点或现实指导建议。请保持理智，切勿模仿。\nS.H.I.T JOURNAL PREPRINT\n本内容纯属整活，不代表任何学术观点或现实指导建议。请保持理智，切勿模仿。\nS.H.I.T JOURNAL PREPRINT\n本内容纯属整活，不代表任何学术观点或现实指导建议。请保持理智，切勿模仿。\nS.H.I.T JOURNAL PREPRINT\n本内容纯属整活，不代表任何学术观点或现实指导建议。请保持理智，切勿模仿。\nS.H.I.T JOURNAL PREPRINT\n本内容纯属整活，不代表任何学术观点或现实指导建议。请保持理智，切勿模仿。\nS.H.I.T JOURNAL PREPRINT\n本内容纯属整活，不代表任何学术观点或现实指导建议。请保持理智，切勿模仿。\nS.H.I.T JOURNAL PREPRINT\n本内容纯属整活，不代表任何学术观点或现实指导建议。请保持理智，切勿模仿。\nS.H.I.T JOURNAL PREPRINT\n本内容纯属整活，不代表任何学术观点或现实指导建议。请保持理智，切勿模仿。\nS.H.I.T JOURNAL PREPRINT\n本内容纯属整活，不代表任何学术观点或现实指导建议。请保持理智，切勿模仿。\n本内容纯属整活，不代表任何学术观点或现实指导建议。请保持理智，切勿模仿。\n← 上一页\n1 / 6\n下一页 →\n评论功能维护中，暂时关闭 / Comments are temporarily disabled\n0 条评论\n默认\n最新\n暂无评论 / No comments yet",
  "meta": {
    "author": "Shitwill Find Itsway",
    "institution": "Sichuan Habber Institute of Technology",
    "discipline": "交叉 / Interdisciplinary",
    "submitted": "2026/2/27 05:22:25",
    "viscosity": "Stringy / 拉丝型"
  },
  "url": "https://shitjournal.org/preprints/c777f933-acb5-4ac0-8f28-0ce99c27ea94",
  "slug": "c777f933-acb5-4ac0-8f28-0ce99c27ea94"
}