{
  "title": "成年男性离散胃肠释放事件的年龄依赖衰减模型研究",
  "subtitle": "",
  "body_text": "← Back to Septic Tank / 返回化粪池\n成年男性离散胃肠释放事件的年龄依赖衰减模型研究\nAuthor / 作者\n生化魔人\nInstitution / 单位\n召唤师峡谷红方野区\nViscosity / 粘度\nHigh-Entropy / 高熵态\nDiscipline / 学科\n工 / Engineering\nSubmitted / 提交时间\n2026/3/4 02:12:05\nSocial Media / 社交媒体\n抖音号：20260630l\nRate / 评价\n登录后可评分 / Sign in to rate\nSign In / 登录\n3.99\n/ 5\n42 ratings / 42个评分\nManuscript / 全文\nS.H.I.T JOURNAL PREPRINT\n本内容纯属整活，不代表任何学术观点或现实指导建议。请保持理智，切勿模仿。\nS.H.I.T JOURNAL PREPRINT\n本内容纯属整活，不代表任何学术观点或现实指导建议。请保持理智，切勿模仿。\nS.H.I.T JOURNAL PREPRINT\n本内容纯属整活，不代表任何学术观点或现实指导建议。请保持理智，切勿模仿。\nS.H.I.T JOURNAL PREPRINT\n本内容纯属整活，不代表任何学术观点或现实指导建议。请保持理智，切勿模仿。\nS.H.I.T JOURNAL PREPRINT\n本内容纯属整活，不代表任何学术观点或现实指导建议。请保持理智，切勿模仿。\nS.H.I.T JOURNAL PREPRINT\n本内容纯属整活，不代表任何学术观点或现实指导建议。请保持理智，切勿模仿。\nS.H.I.T JOURNAL PREPRINT\n本内容纯属整活，不代表任何学术观点或现实指导建议。请保持理智，切勿模仿。\nS.H.I.T JOURNAL PREPRINT\n本内容纯属整活，不代表任何学术观点或现实指导建议。请保持理智，切勿模仿。\nS.H.I.T JOURNAL PREPRINT\n本内容纯属整活，不代表任何学术观点或现实指导建议。请保持理智，切勿模仿。\nS.H.I.T JOURNAL PREPRINT\n本内容纯属整活，不代表任何学术观点或现实指导建议。请保持理智，切勿模仿。\nS.H.I.T JOURNAL PREPRINT\n本内容纯属整活，不代表任何学术观点或现实指导建议。请保持理智，切勿模仿。\nS.H.I.T JOURNAL PREPRINT\n本内容纯属整活，不代表任何学术观点或现实指导建议。请保持理智，切勿模仿。\nS.H.I.T JOURNAL PREPRINT\n本内容纯属整活，不代表任何学术观点或现实指导建议。请保持理智，切勿模仿。\nS.H.I.T JOURNAL PREPRINT\n本内容纯属整活，不代表任何学术观点或现实指导建议。请保持理智，切勿模仿。\nS.H.I.T JOURNAL PREPRINT\n本内容纯属整活，不代表任何学术观点或现实指导建议。请保持理智，切勿模仿。\n本内容纯属整活，不代表任何学术观点或现实指导建议。请保持理智，切勿模仿。\n← 上一页\n1 / 4\n下一页 →\n评论功能维护中，暂时关闭 / Comments are temporarily disabled\n1 条评论\n默认\n最新\n战斗吧\n作者\n🏭 造粪机\n6666\n1天前\n💩\n6",
  "meta": {
    "author": "生化魔人",
    "institution": "召唤师峡谷红方野区",
    "discipline": "工 / Engineering",
    "submitted": "2026/3/4 02:12:05",
    "viscosity": "High-Entropy / 高熵态"
  },
  "url": "https://shitjournal.org/preprints/bde4fabb-773f-4371-a7c0-d4c8fa17c68c",
  "slug": "bde4fabb-773f-4371-a7c0-d4c8fa17c68c"
}