{
  "title": "论药片十字切割对治疗概率的非线性修正：基于“懒人路径”与“单次抛弃协议”的实证研究",
  "subtitle": "",
  "body_text": "← Back to Septic Tank / 返回化粪池\n论药片十字切割对治疗概率的非线性修正：基于“懒人路径”与“单次抛弃协议”的实证研究\nAuthor / 作者\n十六夜芽衣\nInstitution / 单位\nUniversity of TiantianChou\nViscosity / 粘度\nSemi-solid / 半固态\nDiscipline / 学科\n医 / Medical\nSubmitted / 提交时间\n2026/3/2 17:01:36\nSocial Media / 社交媒体\n抖音-小猫用pdd买大米当猫砂七天无理由退款\nRate / 评价\n登录后可评分 / Sign in to rate\nSign In / 登录\n4.31\n/ 5\n38 ratings / 38个评分\nManuscript / 全文\nS.H.I.T JOURNAL PREPRINT\n本内容纯属整活，不代表任何学术观点或现实指导建议。请保持理智，切勿模仿。\nS.H.I.T JOURNAL PREPRINT\n本内容纯属整活，不代表任何学术观点或现实指导建议。请保持理智，切勿模仿。\nS.H.I.T JOURNAL PREPRINT\n本内容纯属整活，不代表任何学术观点或现实指导建议。请保持理智，切勿模仿。\nS.H.I.T JOURNAL PREPRINT\n本内容纯属整活，不代表任何学术观点或现实指导建议。请保持理智，切勿模仿。\nS.H.I.T JOURNAL PREPRINT\n本内容纯属整活，不代表任何学术观点或现实指导建议。请保持理智，切勿模仿。\nS.H.I.T JOURNAL PREPRINT\n本内容纯属整活，不代表任何学术观点或现实指导建议。请保持理智，切勿模仿。\nS.H.I.T JOURNAL PREPRINT\n本内容纯属整活，不代表任何学术观点或现实指导建议。请保持理智，切勿模仿。\nS.H.I.T JOURNAL PREPRINT\n本内容纯属整活，不代表任何学术观点或现实指导建议。请保持理智，切勿模仿。\nS.H.I.T JOURNAL PREPRINT\n本内容纯属整活，不代表任何学术观点或现实指导建议。请保持理智，切勿模仿。\nS.H.I.T JOURNAL PREPRINT\n本内容纯属整活，不代表任何学术观点或现实指导建议。请保持理智，切勿模仿。\nS.H.I.T JOURNAL PREPRINT\n本内容纯属整活，不代表任何学术观点或现实指导建议。请保持理智，切勿模仿。\nS.H.I.T JOURNAL PREPRINT\n本内容纯属整活，不代表任何学术观点或现实指导建议。请保持理智，切勿模仿。\nS.H.I.T JOURNAL PREPRINT\n本内容纯属整活，不代表任何学术观点或现实指导建议。请保持理智，切勿模仿。\nS.H.I.T JOURNAL PREPRINT\n本内容纯属整活，不代表任何学术观点或现实指导建议。请保持理智，切勿模仿。\nS.H.I.T JOURNAL PREPRINT\n本内容纯属整活，不代表任何学术观点或现实指导建议。请保持理智，切勿模仿。\n本内容纯属整活，不代表任何学术观点或现实指导建议。请保持理智，切勿模仿。\n← 上一页\n1 / 5\n下一页 →\n评论功能维护中，暂时关闭 / Comments are temporarily disabled\n2 条评论\n默认\n最新\n棒棒糖不戒烟\n💩💩💩💩💩\n把药片切成四瓣竟然可以提高利用率，学到了学到了\n2天前\n💩\n6\n十六夜芽衣\n作者\n🏭 造粪机\n你也太像水军了\n2天前\n💩\n3",
  "meta": {
    "author": "十六夜芽衣",
    "institution": "University of TiantianChou",
    "discipline": "医 / Medical",
    "submitted": "2026/3/2 17:01:36",
    "viscosity": "Semi-solid / 半固态"
  },
  "url": "https://shitjournal.org/preprints/7b5023e5-1e55-4254-a7aa-90c5744a831a",
  "slug": "7b5023e5-1e55-4254-a7aa-90c5744a831a"
}