{
  "article": {
    "id": "5844d027-3ec6-464d-9845-977226c8919f",
    "title": "量子态班委通知：大学生既看见了又没看懂的叠加态研究",
    "file_name": "5844d027-3ec6-464d-9845-977226c8919f",
    "pdf_url": "https://files.shitjournal.org/5844d027-3ec6-464d-9845-977226c8919f.pdf",
    "tag": "meme",
    "zones": "septic",
    "status": "passed",
    "discipline": "humanities",
    "topic": "nan",
    "co_authors": [],
    "suggestions": "",
    "rating_count": 41,
    "avg_score": 4.341463414634147,
    "my_score": null,
    "created_at": "2026-03-03T17:17:20.830219Z",
    "author": {
      "id": "3a207534-9e69-4337-ad8f-54eb38842ce1",
      "display_name": "Mr晨",
      "avatar_url": null
    }
  },
  "comments": [],
  "fetched_at": "2026-03-10T16:07:17Z"
}