{
  "title": "拓扑锁死与叙事补偿：论“麻薯波比”一根筋变成两头堵叙事下副GOAT范式对中东地缘政治熵值的降维吸纳",
  "subtitle": "",
  "body_text": "← Back to The Latrine / 返回旱厕\n拓扑锁死与叙事补偿：论“麻薯波比”一根筋变成两头堵叙事下副GOAT范式对中东地缘政治熵值的降维吸纳\nAuthor / 作者\n无敌铁头娃\nInstitution / 单位\n李建中东局势分析室\nViscosity / 粘度\nSemi-solid / 半固态\nDiscipline / 学科\n交叉 / Interdisciplinary\nSubmitted / 提交时间\n2026/3/1 18:34:45\nSocial Media / 社交媒体\n抖音：DuckNoB1\nRate / 盲评\n登录后可评分 / Sign in to rate\nSign In / 登录\n评价进度 / Progress: 6 / 30\nManuscript / 全文\nS.H.I.T JOURNAL PREPRINT\n本内容纯属整活，不代表任何学术观点或现实指导建议。请保持理智，切勿模仿。\nS.H.I.T JOURNAL PREPRINT\n本内容纯属整活，不代表任何学术观点或现实指导建议。请保持理智，切勿模仿。\nS.H.I.T JOURNAL PREPRINT\n本内容纯属整活，不代表任何学术观点或现实指导建议。请保持理智，切勿模仿。\nS.H.I.T JOURNAL PREPRINT\n本内容纯属整活，不代表任何学术观点或现实指导建议。请保持理智，切勿模仿。\nS.H.I.T JOURNAL PREPRINT\n本内容纯属整活，不代表任何学术观点或现实指导建议。请保持理智，切勿模仿。\nS.H.I.T JOURNAL PREPRINT\n本内容纯属整活，不代表任何学术观点或现实指导建议。请保持理智，切勿模仿。\nS.H.I.T JOURNAL PREPRINT\n本内容纯属整活，不代表任何学术观点或现实指导建议。请保持理智，切勿模仿。\nS.H.I.T JOURNAL PREPRINT\n本内容纯属整活，不代表任何学术观点或现实指导建议。请保持理智，切勿模仿。\nS.H.I.T JOURNAL PREPRINT\n本内容纯属整活，不代表任何学术观点或现实指导建议。请保持理智，切勿模仿。\nS.H.I.T JOURNAL PREPRINT\n本内容纯属整活，不代表任何学术观点或现实指导建议。请保持理智，切勿模仿。\nS.H.I.T JOURNAL PREPRINT\n本内容纯属整活，不代表任何学术观点或现实指导建议。请保持理智，切勿模仿。\nS.H.I.T JOURNAL PREPRINT\n本内容纯属整活，不代表任何学术观点或现实指导建议。请保持理智，切勿模仿。\nS.H.I.T JOURNAL PREPRINT\n本内容纯属整活，不代表任何学术观点或现实指导建议。请保持理智，切勿模仿。\nS.H.I.T JOURNAL PREPRINT\n本内容纯属整活，不代表任何学术观点或现实指导建议。请保持理智，切勿模仿。\nS.H.I.T JOURNAL PREPRINT\n本内容纯属整活，不代表任何学术观点或现实指导建议。请保持理智，切勿模仿。\n本内容纯属整活，不代表任何学术观点或现实指导建议。请保持理智，切勿模仿。\n← 上一页\n1 / 5\n下一页 →\n评论功能维护中，暂时关闭 / Comments are temporarily disabled\n0 条评论\n默认\n最新\n暂无评论 / No comments yet",
  "meta": {
    "author": "无敌铁头娃",
    "institution": "李建中东局势分析室",
    "discipline": "交叉 / Interdisciplinary",
    "submitted": "2026/3/1 18:34:45",
    "viscosity": "Semi-solid / 半固态"
  },
  "url": "https://shitjournal.org/preprints/48136b93-2fb6-4e9e-b178-ef04e15f5fcc",
  "slug": "48136b93-2fb6-4e9e-b178-ef04e15f5fcc"
}