{
  "title": "晚安消息回复行为与女性好感度相关性实证研究",
  "subtitle": "",
  "body_text": "← Back to Septic Tank / 返回化粪池\n晚安消息回复行为与女性好感度相关性实证研究\nAuthor / 作者\nesls\nInstitution / 单位\n某沙东医专\nViscosity / 粘度\nStringy / 拉丝型\nDiscipline / 学科\n文 / Humanities\nSubmitted / 提交时间\n2026/3/2 18:51:10\nRate / 评价\n登录后可评分 / Sign in to rate\nSign In / 登录\n4.12\n/ 5\n53 ratings / 53个评分\nManuscript / 全文\nS.H.I.T JOURNAL PREPRINT\n本内容纯属整活，不代表任何学术观点或现实指导建议。请保持理智，切勿模仿。\nS.H.I.T JOURNAL PREPRINT\n本内容纯属整活，不代表任何学术观点或现实指导建议。请保持理智，切勿模仿。\nS.H.I.T JOURNAL PREPRINT\n本内容纯属整活，不代表任何学术观点或现实指导建议。请保持理智，切勿模仿。\nS.H.I.T JOURNAL PREPRINT\n本内容纯属整活，不代表任何学术观点或现实指导建议。请保持理智，切勿模仿。\nS.H.I.T JOURNAL PREPRINT\n本内容纯属整活，不代表任何学术观点或现实指导建议。请保持理智，切勿模仿。\nS.H.I.T JOURNAL PREPRINT\n本内容纯属整活，不代表任何学术观点或现实指导建议。请保持理智，切勿模仿。\nS.H.I.T JOURNAL PREPRINT\n本内容纯属整活，不代表任何学术观点或现实指导建议。请保持理智，切勿模仿。\nS.H.I.T JOURNAL PREPRINT\n本内容纯属整活，不代表任何学术观点或现实指导建议。请保持理智，切勿模仿。\nS.H.I.T JOURNAL PREPRINT\n本内容纯属整活，不代表任何学术观点或现实指导建议。请保持理智，切勿模仿。\nS.H.I.T JOURNAL PREPRINT\n本内容纯属整活，不代表任何学术观点或现实指导建议。请保持理智，切勿模仿。\nS.H.I.T JOURNAL PREPRINT\n本内容纯属整活，不代表任何学术观点或现实指导建议。请保持理智，切勿模仿。\nS.H.I.T JOURNAL PREPRINT\n本内容纯属整活，不代表任何学术观点或现实指导建议。请保持理智，切勿模仿。\nS.H.I.T JOURNAL PREPRINT\n本内容纯属整活，不代表任何学术观点或现实指导建议。请保持理智，切勿模仿。\nS.H.I.T JOURNAL PREPRINT\n本内容纯属整活，不代表任何学术观点或现实指导建议。请保持理智，切勿模仿。\nS.H.I.T JOURNAL PREPRINT\n本内容纯属整活，不代表任何学术观点或现实指导建议。请保持理智，切勿模仿。\n本内容纯属整活，不代表任何学术观点或现实指导建议。请保持理智，切勿模仿。\n← 上一页\n1 / 5\n下一页 →\n评论功能维护中，暂时关闭 / Comments are temporarily disabled\n6 条评论\n默认\n最新\nMSc. Wasser, Täglich\n💩💩💩💩💩\n很遗憾作者没有“对203名18-30岁女性为期45天的晚安消息“的具体内容进行完整发布，导致本文可能存在数据造假的伦理问题。建议下次完善方法论部分，做到科学、公开、透明。\n2天前\n💩\n16\n嘴旋肉减\n杀人还要诛心\n2天前\n💩\ne.g.拉屎王\n💩💩💩💩\n没有发布具体聊天记录，可能存在不真实性，如果添上，就可以答辩了。\n2天前\n💩\n7\nTznkqn\n💩💩💩💩💩\n999\n2天前\n💩\n装S用热熔胶烫的M高喊新中国没有奴隶~\n我以前就是在乱撩骚！\n2天前\n💩\n优雅美丽的shit品鉴官\n💩💩💩💩💩\n今后舔狗指南就有文献可以引用了\n2天前\n💩",
  "meta": {
    "author": "esls",
    "institution": "某沙东医专",
    "discipline": "文 / Humanities",
    "submitted": "2026/3/2 18:51:10",
    "viscosity": "Stringy / 拉丝型"
  },
  "url": "https://shitjournal.org/preprints/84b0ea87-a35e-472c-90e1-d7e575c08f96",
  "slug": "84b0ea87-a35e-472c-90e1-d7e575c08f96"
}