{
  "title": "基于深度学习的人类排泄物资源化利用与城市可持续发展耦合机制研究",
  "subtitle": "",
  "body_text": "← Back to Sediment / 返回沉淀区\n基于深度学习的人类排泄物资源化利用与城市可持续发展耦合机制研究\nAuthor / 作者\n空中蜡翔\nInstitution / 单位\n地球厕学院 排泄动力学重点实验室\nViscosity / 粘度\nHigh-Entropy / 高熵态\nDiscipline / 学科\n工 / Engineering\nSubmitted / 提交时间\n2026/3/3 01:12:18\nSocial Media / 社交媒体\n@Teresa\nRate / 评价\n登录后可评分 / Sign in to rate\nSign In / 登录\n3.82\n/ 5\n38 ratings / 38个评分\nManuscript / 全文\nS.H.I.T JOURNAL PREPRINT\n本内容纯属整活，不代表任何学术观点或现实指导建议。请保持理智，切勿模仿。\nS.H.I.T JOURNAL PREPRINT\n本内容纯属整活，不代表任何学术观点或现实指导建议。请保持理智，切勿模仿。\nS.H.I.T JOURNAL PREPRINT\n本内容纯属整活，不代表任何学术观点或现实指导建议。请保持理智，切勿模仿。\nS.H.I.T JOURNAL PREPRINT\n本内容纯属整活，不代表任何学术观点或现实指导建议。请保持理智，切勿模仿。\nS.H.I.T JOURNAL PREPRINT\n本内容纯属整活，不代表任何学术观点或现实指导建议。请保持理智，切勿模仿。\nS.H.I.T JOURNAL PREPRINT\n本内容纯属整活，不代表任何学术观点或现实指导建议。请保持理智，切勿模仿。\nS.H.I.T JOURNAL PREPRINT\n本内容纯属整活，不代表任何学术观点或现实指导建议。请保持理智，切勿模仿。\nS.H.I.T JOURNAL PREPRINT\n本内容纯属整活，不代表任何学术观点或现实指导建议。请保持理智，切勿模仿。\nS.H.I.T JOURNAL PREPRINT\n本内容纯属整活，不代表任何学术观点或现实指导建议。请保持理智，切勿模仿。\nS.H.I.T JOURNAL PREPRINT\n本内容纯属整活，不代表任何学术观点或现实指导建议。请保持理智，切勿模仿。\nS.H.I.T JOURNAL PREPRINT\n本内容纯属整活，不代表任何学术观点或现实指导建议。请保持理智，切勿模仿。\nS.H.I.T JOURNAL PREPRINT\n本内容纯属整活，不代表任何学术观点或现实指导建议。请保持理智，切勿模仿。\nS.H.I.T JOURNAL PREPRINT\n本内容纯属整活，不代表任何学术观点或现实指导建议。请保持理智，切勿模仿。\nS.H.I.T JOURNAL PREPRINT\n本内容纯属整活，不代表任何学术观点或现实指导建议。请保持理智，切勿模仿。\nS.H.I.T JOURNAL PREPRINT\n本内容纯属整活，不代表任何学术观点或现实指导建议。请保持理智，切勿模仿。\n本内容纯属整活，不代表任何学术观点或现实指导建议。请保持理智，切勿模仿。\n← 上一页\n1 / 4\n下一页 →\n评论功能维护中，暂时关闭 / Comments are temporarily disabled\n10 条评论\n默认\n最新\n墨菲特一号大脑\n💩\nterrible format; Need major revision.\n2天前\n💩\n1\n空中蜡翔\n作者\n🏭 造粪机\nwuwuwu~\n2天前\n💩\n吃史不忘拉史人\n💩💩💩💩💩\n数据集呢，我要下饭看\n2天前\n💩\n1\n空中蜡翔\n作者\n🏭 造粪机\n数据涉及全球公厕隐私协议（GTSP），暂无法公开。但欢迎来地球厕学院考察，自带碗筷hhh\n2天前\n💩\nderow\n💩💩💩💩💩\nConsidering open source code?\n2天前\n💩\n1\n空中蜡翔\n作者\n🏭 造粪机\nOpen source code: print('Just imagine it yourself')\n2天前\n💩\n构室品鉴家\n💩💩💩💩💩\nThe most down-to-earth article about real dry toilets.\n2天前\n💩\n空中蜡翔\n作者\n🏭 造粪机\nWell done\n2天前\n💩\n打呼放屁\nGood idaa for humans.\n2天前\n💩\n空中蜡翔\n作者\n🏭 造粪机\nYou've got good taste!\n2天前\n💩",
  "meta": {
    "author": "空中蜡翔",
    "institution": "地球厕学院 排泄动力学重点实验室",
    "discipline": "工 / Engineering",
    "submitted": "2026/3/3 01:12:18",
    "viscosity": "High-Entropy / 高熵态"
  },
  "url": "https://shitjournal.org/preprints/9f6e7ed6-447c-444b-8d56-f483332b193a",
  "slug": "9f6e7ed6-447c-444b-8d56-f483332b193a"
}